releso/__init__.py
releso/__main__.py
releso/__version__.py
releso/agent.py
releso/base_model.py
releso/base_parser.py
releso/callback.py
releso/exceptions.py
releso/feature_extractor.py
releso/geometry.py
releso/gym_environment.py
releso/mesh.py
releso/observation.py
releso/parser_environment.py
releso/shape_parameterization.py
releso/spline.py
releso/spor.py
releso/validation.py
releso/verbosity.py
releso/util/__init__.py
releso/util/caching.py
releso/util/cnn_xns_observations.py
releso/util/load_binary.py
releso/util/logger.py
releso/util/module_import_raiser.py
releso/util/plotting.py
releso/util/reward_helpers.py
releso/util/types.py
releso/util/util_funcs.py
releso/util/visualization.py
releso-0.2.3.dist-info/licenses/LICENSE
releso-0.2.3.dist-info/METADATA
releso-0.2.3.dist-info/WHEEL
releso-0.2.3.dist-info/entry_points.txt
releso-0.2.3.dist-info/top_level.txt
releso-0.2.3.dist-info/RECORD
