Metadata-Version: 2.4
Name: releso
Version: 0.2.3
Author-email: Clemens Fricke <clemens.david.fricke@tuwien.ac.at>
License-Expression: MIT
Project-URL: homepage, https://github.com/tataratat/releso
Project-URL: documentation, https://releso.readthedocs.io/en/latest/
Project-URL: issues, https://github.com/tataratat/releso/issues
Project-URL: repository, https://github.com/tataratat/releso.git
Classifier: Operating System :: OS Independent
Classifier: Programming Language :: Python :: 3.9
Classifier: Programming Language :: Python :: 3.10
Classifier: Programming Language :: Python :: 3.11
Classifier: Programming Language :: Python :: 3.12
Classifier: Programming Language :: Python :: 3.13
Classifier: Natural Language :: English
Classifier: Topic :: Scientific/Engineering
Requires-Python: >=3.9
License-File: LICENSE
Requires-Dist: pydantic<2
Requires-Dist: stable-baselines3
Requires-Dist: tensorboard
Requires-Dist: hjson
Provides-Extra: all
Requires-Dist: splinepy[all]>=0.1.2; extra == "all"
Requires-Dist: torchvision; extra == "all"
Provides-Extra: test
Requires-Dist: pytest; extra == "test"
Requires-Dist: pytest-cov; extra == "test"
Requires-Dist: requests; extra == "test"
Requires-Dist: splinepy[all]>=0.1.2; extra == "test"
Requires-Dist: torchvision; extra == "test"
Provides-Extra: docs
Requires-Dist: sphinx; extra == "docs"
Requires-Dist: sphinx-rtd-theme; extra == "docs"
Requires-Dist: sphinx-jsonschema; extra == "docs"
Provides-Extra: visualize
Requires-Dist: plotly; extra == "visualize"
Requires-Dist: kaleido; extra == "visualize"
Provides-Extra: dev
Requires-Dist: splinepy[all]>=0.1.2; extra == "dev"
Requires-Dist: torchvision; extra == "dev"
Requires-Dist: pytest; extra == "dev"
Requires-Dist: pytest-cov; extra == "dev"
Requires-Dist: sphinx; extra == "dev"
Requires-Dist: sphinx-rtd-theme; extra == "dev"
Requires-Dist: sphinx-jsonschema; extra == "dev"
Requires-Dist: plotly; extra == "dev"
Requires-Dist: kaleido; extra == "dev"
Dynamic: license-file
